{
    "$schema": "https://schema.management.azure.com/schemas/2015-01-01/deploymentParameters.json#",
    "contentVersion": "1.0.0.0",
    "parameters": {
        "location": {
            "value": "eastus"
        },
        "networkInterfaceName": {
            "value": "shirawindowsserver2771"
        },
        "enableAcceleratedNetworking": {
            "value": true
        },
        "networkSecurityGroupName": {
            "value": "shiraWindowsServer2-nsg"
        },
        "networkSecurityGroupRules": {
            "value": [
                {
                    "name": "OpenVPN",
                    "properties": {
                        "priority": 1010,
                        "protocol": "*",
                        "access": "Allow",
                        "direction": "Inbound",
                        "sourceApplicationSecurityGroups": [],
                        "destinationApplicationSecurityGroups": [],
                        "sourceAddressPrefix": "*",
                        "sourcePortRange": "*",
                        "destinationAddressPrefix": "*",
                        "destinationPortRange": "1194"
                    }
                },
                {
                    "name": "SSL",
                    "properties": {
                        "priority": 1020,
                        "protocol": "*",
                        "access": "Allow",
                        "direction": "Inbound",
                        "sourceApplicationSecurityGroups": [],
                        "destinationApplicationSecurityGroups": [],
                        "sourceAddressPrefix": "*",
                        "sourcePortRange": "*",
                        "destinationAddressPrefix": "*",
                        "destinationPortRange": "443"
                    }
                },
                {
                    "name": "default-allow-rdp",
                    "properties": {
                        "priority": 1000,
                        "protocol": "TCP",
                        "access": "Allow",
                        "direction": "Inbound",
                        "sourceApplicationSecurityGroups": [],
                        "destinationApplicationSecurityGroups": [],
                        "sourceAddressPrefix": "*",
                        "sourcePortRange": "*",
                        "destinationAddressPrefix": "*",
                        "destinationPortRange": "3389"
                    }
                }
            ]
        },
        "subnetName": {
            "value": "Subnet"
        },
        "virtualNetworkId": {
            "value": "/subscriptions/a8108c2b-496c-424d-8347-ecc8afb6384c/resourceGroups/ShiraStorageAccount-rg/providers/Microsoft.Network/virtualNetworks/MyVNET"
        },
        "publicIpAddressName": {
            "value": "shiraWindowsServer2-ip"
        },
        "publicIpAddressType": {
            "value": "Static"
        },
        "publicIpAddressSku": {
            "value": "Standard"
        },
        "virtualMachineName": {
            "value": "shiraWindowsServer2"
        },
        "virtualMachineComputerName": {
            "value": "shiraWindowsSer"
        },
        "virtualMachineRG": {
            "value": "ShiraStorageAccount-rg"
        },
        "osDiskType": {
            "value": "Premium_LRS"
        },
        "virtualMachineSize": {
            "value": "Standard_D2s_v3"
        },
        "adminUsername": {
            "value": "shira.zadok"
        },
        "adminPassword": {
            "value": "ShSz_2086"
        },
        "patchMode": {
            "value": "AutomaticByOS"
        },
        "enableHotpatching": {
            "value": false
        },
        "zone": {
            "value": "3"
        }
    }
}
